filterbib/__init__.py
filterbib/filter_bib
filterbib/read_bib
filterbib-0.1.0.data/scripts/filter_bib
filterbib-0.1.0.data/scripts/read_bib
filterbib-0.1.0.dist-info/LICENSE
filterbib-0.1.0.dist-info/METADATA
filterbib-0.1.0.dist-info/WHEEL
filterbib-0.1.0.dist-info/top_level.txt
filterbib-0.1.0.dist-info/RECORD
