Metadata-Version: 2.2
Name: filterbib
Version: 0.1.0
Summary: A Python package that includes a Python and Bash script to filter particular fields from a bib-file
Author-email: Jurjen Heij <jurjenheij@gmail.com>
License: Creative Commons Legal Code
Requires-Python: >=3.9
License-File: LICENSE
Requires-Dist: pybtex
